{"EventName":"StartSession","TimestampUTC":1719947260.066000,"RecordId":0,"ProjectName":"GoM","ProjectID":"00000000000000000000000000000000","Session_ID":"{D01CBB6B-45C4-2459-C979-5A8A77712D50}","Session_Label":"","Session_StartUTC":1719947260.066,"Build_Configuration":"Development","Build_IsInternalBuild":false,"Build_IsPerforceBuild":false,"Build_IsPromotedBuild":true,"Build_BranchName":"++ue5+release-5.4","Build_Changelist":33871570,"Hardware_Platform":"Windows","Hardware_GPU":"","Hardware_CPU":"13th Gen Intel(R) Core(TM) i7-13700K","Hardware_CPU_Cores_Physical":16,"Hardware_CPU_Cores_Logical":24,"Hardware_RAM":34088235008,"Hardware_ComputerName":"GOD-KING","Config_IsEditor":true,"Config_IsUnattended":true,"Config_IsBuildMachine":false,"Config_IsRunningCommandlet":true,"Config_IsDebuggerPresent":false}
{"EventName":"Editor.AssetRegistry.Startup","TimestampUTC":1719947262.189000,"RecordId":1,"ProjectName":"GoM","ProjectID":"00000000000000000000000000000000","Session_ID":"{D01CBB6B-45C4-2459-C979-5A8A77712D50}","Session_Label":"","Session_StartUTC":1719947260.066,"Build_Configuration":"Development","Build_IsInternalBuild":false,"Build_IsPerforceBuild":false,"Build_IsPromotedBuild":true,"Build_BranchName":"++ue5+release-5.4","Build_Changelist":33871570,"Hardware_Platform":"Windows","Hardware_GPU":"","Hardware_CPU":"13th Gen Intel(R) Core(TM) i7-13700K","Hardware_CPU_Cores_Physical":16,"Hardware_CPU_Cores_Logical":24,"Hardware_RAM":34088235008,"Hardware_ComputerName":"GOD-KING","Config_IsEditor":true,"Config_IsUnattended":true,"Config_IsBuildMachine":false,"Config_IsRunningCommandlet":true,"Config_IsDebuggerPresent":false,"SchemaVersion":1,"Duration":0.000207,"StartedAsyncGather":false}
{"EventName":"Editor.AssetRegistry.SynchronousScan","TimestampUTC":1719947265.528000,"RecordId":2,"ProjectName":"GoM","ProjectID":"00000000000000000000000000000000","Session_ID":"{D01CBB6B-45C4-2459-C979-5A8A77712D50}","Session_Label":"","Session_StartUTC":1719947260.066,"Build_Configuration":"Development","Build_IsInternalBuild":false,"Build_IsPerforceBuild":false,"Build_IsPromotedBuild":true,"Build_BranchName":"++ue5+release-5.4","Build_Changelist":33871570,"Hardware_Platform":"Windows","Hardware_GPU":"","Hardware_CPU":"13th Gen Intel(R) Core(TM) i7-13700K","Hardware_CPU_Cores_Physical":16,"Hardware_CPU_Cores_Logical":24,"Hardware_RAM":34088235008,"Hardware_ComputerName":"GOD-KING","Config_IsEditor":true,"Config_IsUnattended":true,"Config_IsBuildMachine":false,"Config_IsRunningCommandlet":true,"Config_IsDebuggerPresent":false,"SchemaVersion":1,"Directories":["/Game"],"Files":[],"Flags":"WaitForInMemoryObjects","NumFoundAssets":16498,"DurationSeconds":0.594118,"InitialSearchStarted":false,"InitialSearchCompleted":true}
